elasticube/__init__.py
elasticube/__init__.pyi
elasticube/_elasticube.abi3.so
elasticube/display.py
elasticube/py.typed
elasticube/serialization.py
elasticube/streaming.py
elasticube/viz.py
elasticube-1.1.1.dist-info/METADATA
elasticube-1.1.1.dist-info/WHEEL
elasticube-1.1.1.dist-info/RECORD
