Metadata-Version: 2.4
Name: elasticube
Version: 1.1.1
Classifier: Development Status :: 5 - Production/Stable
Classifier: Intended Audience :: Developers
Classifier: License :: OSI Approved :: MIT License
Classifier: License :: OSI Approved :: Apache Software License
Classifier: Programming Language :: Rust
Classifier: Programming Language :: Python :: 3
Classifier: Programming Language :: Python :: 3.8
Classifier: Programming Language :: Python :: 3.9
Classifier: Programming Language :: Python :: 3.10
Classifier: Programming Language :: Python :: 3.11
Classifier: Programming Language :: Python :: 3.12
Requires-Dist: pyarrow>=14.0.0
Requires-Dist: pandas>=2.0.0
Requires-Dist: polars>=0.19.0 ; extra == 'all'
Requires-Dist: matplotlib>=3.5.0 ; extra == 'all'
Requires-Dist: seaborn>=0.12.0 ; extra == 'all'
Requires-Dist: ipython>=8.0.0 ; extra == 'all'
Requires-Dist: jupyter>=1.0.0 ; extra == 'all'
Requires-Dist: notebook>=6.5.0 ; extra == 'all'
Requires-Dist: pytest>=7.0 ; extra == 'dev'
Requires-Dist: pytest-asyncio>=0.21 ; extra == 'dev'
Requires-Dist: maturin>=1.0 ; extra == 'dev'
Requires-Dist: ipython>=8.0.0 ; extra == 'jupyter'
Requires-Dist: jupyter>=1.0.0 ; extra == 'jupyter'
Requires-Dist: notebook>=6.5.0 ; extra == 'jupyter'
Requires-Dist: polars>=0.19.0 ; extra == 'polars'
Requires-Dist: matplotlib>=3.5.0 ; extra == 'viz'
Requires-Dist: seaborn>=0.12.0 ; extra == 'viz'
Provides-Extra: all
Provides-Extra: dev
Provides-Extra: jupyter
Provides-Extra: polars
Provides-Extra: viz
Summary: High-performance OLAP cube library with Rust backend, featuring native DataFrame support, streaming data loading, and dynamic aggregations
Keywords: olap,analytics,cube,arrow,datafusion
Home-Page: https://github.com/horizonanalytic/elasticube
Author-email: Cache McClure <cache.mcclure@gmail.com>
Maintainer: Horizon Analytic Studios
License: MIT OR Apache-2.0
Requires-Python: >=3.8
Project-URL: Documentation, https://github.com/horizonanalytic/elasticube/tree/main/elasticube-py
Project-URL: Homepage, https://github.com/horizonanalytic/elasticube
Project-URL: Issues, https://github.com/horizonanalytic/elasticube/issues
Project-URL: Repository, https://github.com/horizonanalytic/elasticube
